Metadata-Version: 1.0
Name: smartsearch
Version: 1.0.3
Summary: A module that searches various internet sources to find direct answers to queries.
Home-page: https://github.com/ironman5366/smartsearch
Author: Will Beddow
Author-email: will@willbeddow.com
License: MIT
Platform: UNKNOWN
